statistics_bioresearch/__init__.py
statistics_bioresearch/constants.py
statistics_bioresearch/fisher.py
statistics_bioresearch/kaerber.py
statistics_bioresearch/wilson.py
statistics_bioresearch-0.0.3.dist-info/LICENSE
statistics_bioresearch-0.0.3.dist-info/METADATA
statistics_bioresearch-0.0.3.dist-info/WHEEL
statistics_bioresearch-0.0.3.dist-info/top_level.txt
statistics_bioresearch-0.0.3.dist-info/RECORD
